{
  "gitSyncId": "68a8672a233367326da8b15f_2fc38163-4eab-4f04-8a2c-8f89c5cc9a37",
  "id": "Ver_Facturas_Update_public_facturas1",
  "pluginId": "postgres-plugin",
  "pluginType": "DB",
  "unpublishedAction": {
    "actionConfiguration": {
      "body": "UPDATE public.facturas SET \"fac_nro\"= '{{Table1.updatedRow.fac_nro}}', \"fac_tipo\"= '{{Table1.updatedRow.fac_tipo}}', \"cae_nro\"= '{{Table1.updatedRow.cae_nro}}', \"cae_venc\"= '{{Table1.updatedRow.cae_venc}}', \"fac_fecha\"= '{{Table1.updatedRow.fac_fecha}}', \"facturador_id\"= '{{Table1.updatedRow.facturador_id}}', \"receptor_id\"= '{{Table1.updatedRow.receptor_id}}', \"pto_vnta\"= '{{Table1.updatedRow.pto_vnta}}', \"fac_fecha_desde\"= '{{Table1.updatedRow.fac_fecha_desde}}', \"fac_fecha_hasta\"= '{{Table1.updatedRow.fac_fecha_hasta}}', \"fac_fecha_vto\"= '{{Table1.updatedRow.fac_fecha_vto}}', \"imp_total\"= '{{Table1.updatedRow.imp_total}}', \"fac_concepto\"= '{{Table1.updatedRow.fac_concepto}}', \"pdf_url\"= '{{Table1.updatedRow.pdf_url}}', \"created_at\"= '{{Table1.updatedRow.created_at}}', \"created_by\"= '{{Table1.updatedRow.created_by}}', \"updated_at\"= '{{Table1.updatedRow.updated_at}}', \"updated_by\"= '{{Table1.updatedRow.updated_by}}' WHERE \"id\"= {{Table1.updatedRow.id}};",
      "encodeParamsToggle": true,
      "paginationType": "NONE",
      "pluginSpecifiedTemplates": [
        {
          "value": false
        }
      ],
      "timeoutInMillisecond": 10000
    },
    "confirmBeforeExecute": false,
    "datasource": {
      "id": "facturador_mat30_db",
      "isAutoGenerated": false,
      "name": "facturador_mat30_db",
      "pluginId": "postgres-plugin"
    },
    "dynamicBindingPathList": [
      {
        "key": "body"
      }
    ],
    "executeOnLoad": false,
    "name": "Update_public_facturas1",
    "pageId": "Ver_Facturas",
    "userSetOnLoad": false
  }
}