{
  "animateLoading": true,
  "borderRadius": "{{appsmith.theme.borderRadius.appBorderRadius}}",
  "bottomRow": 34,
  "boxShadow": "none",
  "buttonColor": "{{appsmith.theme.colors.primaryColor}}",
  "buttonVariant": "PRIMARY",
  "disabledWhenInvalid": true,
  "dynamicBindingPathList": [
    {
      "key": "buttonColor"
    },
    {
      "key": "borderRadius"
    }
  ],
  "dynamicTriggerPathList": [],
  "isDefaultClickDisabled": true,
  "isDisabled": false,
  "isLoading": false,
  "isVisible": true,
  "key": "sj0se4d3q7",
  "leftColumn": 47,
  "minWidth": 120,
  "mobileBottomRow": 37,
  "mobileLeftColumn": 46,
  "mobileRightColumn": 62,
  "mobileTopRow": 33,
  "needsErrorInfo": false,
  "parentId": "prp0gamzzr",
  "placement": "CENTER",
  "recaptchaType": "V3",
  "renderMode": "CANVAS",
  "resetFormOnClick": true,
  "responsiveBehavior": "hug",
  "rightColumn": 63,
  "text": "Agregar",
  "topRow": 30,
  "type": "BUTTON_WIDGET",
  "version": 1,
  "widgetId": "90p6k4e5ch",
  "widgetName": "agregar_f"
}